{"total":16,"serverTime":1616922279413,"videoList":[{"num":1,"video_id":"VIDE9EUezRSJ47ZwF83RYmf2201221","video_title":"[视频]中央军委主席习近平签署命令发布《军队军事职业教育条例（试行）》","video_image":"https://p2.img.cctvpic.com/fmspic/2020/12/21/913c8bf7b5c8406185a0d9de888edb94-180.jpg","guid":"913c8bf7b5c8406185a0d9de888edb94","video_length":"00:01:19","video_tag":"中央军委主席习近平签署命令发布《军队军事职业教育条例（试行）》","video_url":"https://tv.cctv.com/2020/12/21/VIDE9EUezRSJ47ZwF83RYmf2201221.shtml","page_id":"PAGE4y8I53JvSWE8DlRSMlbu160121","edit_mode":"1","brief":"中央军委主席习近平签署命令发布《军队军事职业教育条例（试行）》。","pub_date":"2020-12-21 19:07:02","news_hl_tag":"中国领导人,人民领袖","video_detail":{"id":"VIDE9EUezRSJ47ZwF83RYmf2201221","guid":"913c8bf7b5c8406185a0d9de888edb94","title":"[视频]中央军委主席习近平签署命令发布《军队军事职业教育条例（试行）》","source":"央视网","pubtime":"2020-12-21 19:07:02","content":"<p>央视网消息（新闻联播）：中央军委主席习近平日前签署命令，发布《军队军事职业教育条例（试行）》，自2021年1月1日起施行。</p>\r\n<p>《条例》深入贯彻习近平强军思想，深入贯彻新时代军事教育方针，围绕培养德才兼备的高素质、专业化新型军事人才，着眼构建形成时时学、处处学、人人学、终身学的格局，坚持正确政治方向，坚持紧贴使命任务、岗位履职、职业发展，完善网络化、开放式、全覆盖军事职业教育体系，从宏观上建立军事职业教育制度机制，对于推动军事职业教育建设发展、构建新型军事人才培养体系，具有重要意义。</p>\r\n<p>《条例》共8章43条，界定了军事职业教育对象范围、组织形式、时代要求等基本内涵，构建了中央军委统一领导下的军事职业教育领导管理体系，对教育任务、学习管理、支撑保障、激励与监督等内容作了系统规范，为激发官兵学习动力、规范工作管理运行提供了有力制度保证。</p>","logo":"https://p2.img.cctvpic.com/fmspic/2020/12/21/913c8bf7b5c8406185a0d9de888edb94-180.jpg","url":"https://tv.cctv.com/2020/12/21/VIDE9EUezRSJ47ZwF83RYmf2201221.shtml","catalog":"","allow_share":"1","allow_praise":"1","allow_comment":"1","channel_id":"CHAL1450952056131267","topic_id":"TOPC1451528971114112","primary_page_id":"PAGE4y8I53JvSWE8DlRSMlbu160121","desc":"中央军委主席习近平签署命令发布《军队军事职业教育条例（试行）》","brief":"中央军委主席习近平签署命令发布《军队军事职业教育条例（试行）》。","tag":"中央军委主席习近平签署命令发布《军队军事职业教育条例（试行）》"}},{"num":2,"video_id":"VIDE1pXPS33bVdtYcAqCZXOk201221","video_title":"[视频]凝心聚力 乘势而上 构建新发展格局——中央经济工作会议精神在全国各地引起强烈反响","video_image":"https://p3.img.cctvpic.com/fmspic/2020/12/21/b23db6449a134b36bcf5451893a98103-180.jpg","guid":"b23db6449a134b36bcf5451893a98103","video_length":"00:06:38","video_tag":"凝心聚力,乘势而上,构建新发展格局——中央经济工作会议精神在全国各地引起强烈反响","video_url":"https://tv.cctv.com/2020/12/21/VIDE1pXPS33bVdtYcAqCZXOk201221.shtml","page_id":"PAGE4y8I53JvSWE8DlRSMlbu160121","edit_mode":"1","brief":"凝心聚力，乘势而上，构建新发展格局——中央经济工作会议精神在全国各地引起强烈反响。","pub_date":"2020-12-21 19:10:01","news_hl_tag":"中国经济","video_detail":{"id":"VIDE1pXPS33bVdtYcAqCZXOk201221","guid":"b23db6449a134b36bcf5451893a98103","title":"[视频]凝心聚力 乘势而上 构建新发展格局——中央经济工作会议精神在全国各地引起强烈反响","source":"央视网","pubtime":"2020-12-21 19:10:01","content":"<p>央视网消息（新闻联播）：中央经济工作会议精神在社会各界引发强烈反响。广大干部群众表示，过去一年，在以习近平同志为核心的党中央坚强领导下，我们战胜艰难险阻，经济社会发展取得历史性成就。新的一年，我们要认真学习贯彻中央经济工作会议精神，凝心聚力、乘势而上，确保“十四五”开好局，为全面建设社会主义现代化国家贡献力量。</p>\r\n<p>会议指出，今年是新中国历史上极不平凡的一年。面对新冠肺炎疫情和经济社会发展的复杂严峻形势，以习近平同志为核心的党中央保持战略定力，准确判断形势，精心谋划部署，果断采取行动，团结带领全国各族人民艰苦努力，统筹疫情防控和经济社会发展取得重大成果。</p>\r\n<p>会议指出，我国经济实力、科技实力、综合国力和人民生活水平又跃上新的大台阶，全面建成小康社会胜利在望。我国脱贫攻坚成果举世瞩目，今年，全国预计有5575万农村贫困人口摆脱贫困。</p>\r\n<p>会议部署了明年经济工作的八项重点任务，指出产业链供应链安全稳定是构建新发展格局的基础。不久前，上海、江苏、浙江、安徽相关部门签署协议，共同推进长三角新型产业一体化高质量发展。</p>\r\n<p>会议强调，构建新发展格局，必须构建高水平社会主义市场经济体制，实行高水平对外开放，推动改革和开放相互促进。在粤港澳大湾区，企业商事登记实现“一网通办”，跨境要素流动更加便捷，一个更加开放的国际一流湾区正在形成。</p>\r\n<p>住房问题关系民生福祉。会议指出要解决好大城市住房突出问题。地处北京市南三环的这4栋新楼是北京首批在集体用地上建的租赁住房，今年5月底投入使用。刚工作不久的尹雪飞是这里的首批住户。</p>\r\n<p>站在“两个一百年”奋斗目标的历史交汇点上，广大干部群众表示，要更加紧密地团结在以习近平同志为核心的党中央周围，齐心协力、开拓进取，为全面建设社会主义现代化国家、实现中华民族伟大复兴的中国梦贡献力量！</p>","logo":"https://p3.img.cctvpic.com/fmspic/2020/12/21/b23db6449a134b36bcf5451893a98103-180.jpg","url":"https://tv.cctv.com/2020/12/21/VIDE1pXPS33bVdtYcAqCZXOk201221.shtml","catalog":"","allow_share":"1","allow_praise":"1","allow_comment":"1","channel_id":"CHAL1450952056131267","topic_id":"TOPC1451528971114112","primary_page_id":"PAGE4y8I53JvSWE8DlRSMlbu160121","desc":"凝心聚力 乘势而上 构建新发展格局——中央经济工作会议精神在全国各地引起强烈反响","brief":"凝心聚力，乘势而上，构建新发展格局——中央经济工作会议精神在全国各地引起强烈反响。","tag":"凝心聚力,乘势而上,构建新发展格局——中央经济工作会议精神在全国各地引起强烈反响"}},{"num":3,"video_id":"VIDEgXnoSuh7vkckiG9BpW9v201221","video_title":"[视频]人民日报评论员文章：深刻把握在严峻挑战下做好经济工作的规律性认识——论学习贯彻中央经济工作会议精神","video_image":"https://p5.img.cctvpic.com/fmspic/2020/12/21/0c020691ee6d492a98b61d9fac46d9e1-180.jpg","guid":"0c020691ee6d492a98b61d9fac46d9e1","video_length":"00:00:13","video_tag":"人民日报评论员文章,经济工作","video_url":"https://tv.cctv.com/2020/12/21/VIDEgXnoSuh7vkckiG9BpW9v201221.shtml","page_id":"PAGE4y8I53JvSWE8DlRSMlbu160121","edit_mode":"1","brief":"人民日报评论员文章：深刻把握在严峻挑战下做好经济工作的规律性认识——论学习贯彻中央经济工作会议精神。","pub_date":"2020-12-21 19:13:02","news_hl_tag":"中国经济","video_detail":{"id":"VIDEgXnoSuh7vkckiG9BpW9v201221","guid":"0c020691ee6d492a98b61d9fac46d9e1","title":"[视频]人民日报评论员文章：深刻把握在严峻挑战下做好经济工作的规律性认识——论学习贯彻中央经济工作会议精神","source":"央视网","pubtime":"2020-12-21 19:13:02","content":"<p>央视网消息（新闻联播）：今天（12月21日）出版的人民日报发表评论员文章，题目是《深刻把握在严峻挑战下做好经济工作的规律性认识——论学习贯彻中央经济工作会议精神》。</p>","logo":"https://p5.img.cctvpic.com/fmspic/2020/12/21/0c020691ee6d492a98b61d9fac46d9e1-180.jpg","url":"https://tv.cctv.com/2020/12/21/VIDEgXnoSuh7vkckiG9BpW9v201221.shtml","catalog":"","allow_share":"1","allow_praise":"1","allow_comment":"1","channel_id":"CHAL1450952056131267","topic_id":"TOPC1451528971114112","primary_page_id":"PAGE4y8I53JvSWE8DlRSMlbu160121","desc":"人民日报评论员文章：深刻把握在严峻挑战下做好经济工作的规律性认识","brief":"人民日报评论员文章：深刻把握在严峻挑战下做好经济工作的规律性认识——论学习贯彻中央经济工作会议精神。","tag":"人民日报评论员文章,经济工作"}},{"num":4,"video_id":"VIDEMBZraOrNImq4MvYQSCVR201221","video_title":"[视频]【央视快评】科学精准实施宏观政策","video_image":"https://p4.img.cctvpic.com/fmspic/2020/12/21/d9ee491c6e894907a1005ea1f1edc67f-180.jpg","guid":"d9ee491c6e894907a1005ea1f1edc67f","video_length":"00:00:06","video_tag":"[视频]【央视快评】科学精准实施宏观政策","video_url":"https://tv.cctv.com/2020/12/21/VIDEMBZraOrNImq4MvYQSCVR201221.shtml","page_id":"PAGE4y8I53JvSWE8DlRSMlbu160121","edit_mode":"1","brief":"【央视快评】科学精准实施宏观政策。","pub_date":"2020-12-21 19:14:02","news_hl_tag":"央视评论","video_detail":{"id":"VIDEMBZraOrNImq4MvYQSCVR201221","guid":"d9ee491c6e894907a1005ea1f1edc67f","title":"[视频]【央视快评】科学精准实施宏观政策","source":"央视网","pubtime":"2020-12-21 19:14:02","content":"<p>央视网消息（新闻联播）：本台播发央视快评《科学精准实施宏观政策》。</p>","logo":"https://p4.img.cctvpic.com/fmspic/2020/12/21/d9ee491c6e894907a1005ea1f1edc67f-180.jpg","url":"https://tv.cctv.com/2020/12/21/VIDEMBZraOrNImq4MvYQSCVR201221.shtml","catalog":"","allow_share":"1","allow_praise":"1","allow_comment":"1","channel_id":"CHAL1450952056131267","topic_id":"TOPC1451528971114112","primary_page_id":"PAGE4y8I53JvSWE8DlRSMlbu160121","desc":"[视频]【央视快评】科学精准实施宏观政策","brief":"【央视快评】科学精准实施宏观政策。","tag":"[视频]【央视快评】科学精准实施宏观政策"}},{"num":5,"video_id":"VIDED3HfldrvgRxAwEZkfFW7201221","video_title":"[视频]栗战书出席深入学习贯彻习近平总书记关于坚持和完善人民代表大会制度的重要思想交流会","video_image":"https://p4.img.cctvpic.com/fmspic/2020/12/21/0e4fcc2d368b4c258f13fdae285a7f08-1.jpg","guid":"0e4fcc2d368b4c258f13fdae285a7f08","video_length":"00:02:02","video_tag":"栗战书出席深入学习贯彻习近平总书记关于坚持和完善人民代表大会制度的重要思想交流会","video_url":"https://tv.cctv.com/2020/12/21/VIDED3HfldrvgRxAwEZkfFW7201221.shtml","page_id":"PAGE4y8I53JvSWE8DlRSMlbu160121","edit_mode":"1","brief":"栗战书出席深入学习贯彻习近平总书记关于坚持和完善人民代表大会制度的重要思想交流会。","pub_date":"2020-12-21 19:16:02","news_hl_tag":"中国领导人,人民领袖","video_detail":{"id":"VIDED3HfldrvgRxAwEZkfFW7201221","guid":"0e4fcc2d368b4c258f13fdae285a7f08","title":"[视频]栗战书出席深入学习贯彻习近平总书记关于坚持和完善人民代表大会制度的重要思想交流会","source":"央视网","pubtime":"2020-12-21 19:16:02","content":"<p>央视网消息（新闻联播）：深入学习贯彻习近平总书记关于坚持和完善人民代表大会制度的重要思想，坚持党的领导、人民当家作主、依法治国有机统一交流会21日在京举行。中共中央政治局常委、全国人大常委会委员长栗战书出席会议并讲话强调，要深入学习习近平法治思想和习近平总书记关于坚持和完善人民代表大会制度的重要思想，坚持党的领导、人民当家作主、依法治国有机统一，在全面建设社会主义现代化国家新征程上更好发挥人大职能作用。</p>\r\n<p>栗战书指出，人民代表大会制度是“三者有机统一”的根本政治制度安排，是打通坚持党的领导、人民当家作主、依法治国有机统一的重要制度平台和有效载体，要将三者统一于中国特色社会主义民主政治伟大实践，统一于全面建设社会主义现代化国家伟大实践，统一于坚持和完善中国特色社会主义制度、走中国特色社会主义道路的伟大实践。坚持人民代表大会制度，本身就是体现人民当家作主，特别需要重视和坚持两点，一是始终坚持党中央的集中统一领导，二是始终坚持走中国特色社会主义政治发展道路。</p>\r\n<p>栗战书强调，要自觉把人大工作放在党和国家工作大局中来谋划、来推进。一是把坚持党的全面领导作为人大工作的首要政治原则，以习近平新时代中国特色社会主义思想指导人大工作，确保人大工作正确方向。二是通过人民代表大会制度充分保证人民当家作主，使人民当家作主更加具体地、现实地、有效地落实到国家政治生活之中。三是继续推进法律体系的完善，丰富立法形式，既要“大块头”也要“小快灵”，提高立法质量。</p>\r\n<p>王晨主持学习交流会，与会同志开展交流研讨。  </p>","logo":"https://p4.img.cctvpic.com/fmspic/2020/12/21/0e4fcc2d368b4c258f13fdae285a7f08-1.jpg","url":"https://tv.cctv.com/2020/12/21/VIDED3HfldrvgRxAwEZkfFW7201221.shtml","catalog":"","allow_share":"1","allow_praise":"1","allow_comment":"1","channel_id":"CHAL1450952056131267","topic_id":"TOPC1451528971114112","primary_page_id":"PAGE4y8I53JvSWE8DlRSMlbu160121","desc":"栗战书出席深入学习贯彻习近平总书记关于坚持和完善人民代表大会制度的重要思想交流会","brief":"栗战书出席深入学习贯彻习近平总书记关于坚持和完善人民代表大会制度的重要思想交流会。","tag":"栗战书出席深入学习贯彻习近平总书记关于坚持和完善人民代表大会制度的重要思想交流会"}},{"num":6,"video_id":"VIDEQjlqaItnQjurWqHhttMi201221","video_title":"[视频]栗战书同韩国国会议长举行会谈","video_image":"https://p5.img.cctvpic.com/fmspic/2020/12/21/6a33bfd0496d463c8e88a4fa7855471d-180.jpg","guid":"6a33bfd0496d463c8e88a4fa7855471d","video_length":"00:01:55","video_tag":"栗战书同韩国国会议长举行会谈","video_url":"https://tv.cctv.com/2020/12/21/VIDEQjlqaItnQjurWqHhttMi201221.shtml","page_id":"PAGE4y8I53JvSWE8DlRSMlbu160121","edit_mode":"1","brief":"栗战书同韩国国会议长举行会谈。","pub_date":"2020-12-21 19:18:03","news_hl_tag":"中国领导人,大国外交","video_detail":{"id":"VIDEQjlqaItnQjurWqHhttMi201221","guid":"6a33bfd0496d463c8e88a4fa7855471d","title":"[视频]栗战书同韩国国会议长举行会谈","source":"央视网","pubtime":"2020-12-21 19:18:03","content":"<p>央视网消息（新闻联播）：全国人大常委会委员长栗战书21日在人民大会堂以视频方式同韩国国会议长朴炳锡举行会谈。</p>\r\n<p>栗战书说，中韩互为友好近邻和重要合作伙伴。在习近平主席和文在寅总统战略引领下，中韩关系保持良好发展势头。双方互信日益加深，互利合作不断深化，友好交往更加活跃，两国关系充满活力。双方要始终立足大局、着眼长远，尊重彼此核心利益和重大关切，加强各层级沟通，扩大友好共识，确保两国关系始终沿着正确方向行稳致远。</p>\r\n<p>栗战书强调，今年以来，中韩双方携手抗疫、共克时艰，树立了国际抗疫合作典范，也为两国友好增添了新的内涵。要继续发挥好联防联控、“快捷通道”的作用，积极探讨和推进疫苗和药物研发使用等合作，携手控制疫情。加快发展战略对接，推动第三方市场合作早见实质成果，早日完成自贸协定第二阶段谈判。以“中韩文化交流年”为契机，进一步活跃教育、体育、青少年、学术、地方等领域交流。共同维护和促进朝鲜半岛和平发展，加强多边框架内的沟通与协调，维护国际公平正义，推动构建人类命运共同体。两国立法机构要继续发挥好交流机制作用，加强在治国理政、发展经济、改善民生等领域的互学互鉴，为推动两国关系和服务各自国家发展作出积极贡献。</p>\r\n<p>朴炳锡说，韩国国会愿不断加强和中国全国人大的交流合作，为增进两国友好的社会和民意基础，促进韩中战略合作伙伴关系发展和地区和平稳定作出积极贡献。</p>\r\n<p>王东明参加会谈。</p>","logo":"https://p5.img.cctvpic.com/fmspic/2020/12/21/6a33bfd0496d463c8e88a4fa7855471d-180.jpg","url":"https://tv.cctv.com/2020/12/21/VIDEQjlqaItnQjurWqHhttMi201221.shtml","catalog":"","allow_share":"1","allow_praise":"1","allow_comment":"1","channel_id":"CHAL1450952056131267","topic_id":"TOPC1451528971114112","primary_page_id":"PAGE4y8I53JvSWE8DlRSMlbu160121","desc":"栗战书同韩国国会议长举行会谈","brief":"栗战书同韩国国会议长举行会谈。","tag":"栗战书同韩国国会议长举行会谈"}},{"num":7,"video_id":"VIDEM0th5wrG6NHuvBq87cfv201221","video_title":"[视频]汪洋主持召开全国政协主席会议","video_image":"https://p5.img.cctvpic.com/fmspic/2020/12/21/a29f0a0ad92245fd9f56b429ddfe6f70-1.jpg","guid":"a29f0a0ad92245fd9f56b429ddfe6f70","video_length":"00:02:35","video_tag":"汪洋主持召开全国政协主席会议","video_url":"https://tv.cctv.com/2020/12/21/VIDEM0th5wrG6NHuvBq87cfv201221.shtml","page_id":"PAGE4y8I53JvSWE8DlRSMlbu160121","edit_mode":"1","brief":"汪洋主持召开全国政协主席会议。","pub_date":"2020-12-21 19:21:02","news_hl_tag":"人大政协,中国领导人","video_detail":{"id":"VIDEM0th5wrG6NHuvBq87cfv201221","guid":"a29f0a0ad92245fd9f56b429ddfe6f70","title":"[视频]汪洋主持召开全国政协主席会议","source":"央视网","pubtime":"2020-12-21 19:21:02","content":"<p>央视网消息（新闻联播）：政协第十三届全国委员会第四十七次主席会议21日在京举行，传达学习中央经济工作会议精神，研究部署相关工作。中共中央政治局常委、全国政协主席汪洋主持会议并讲话。</p><p>汪洋指出，中央经济工作会议深入分析当前经济形势，全面部署明年经济工作，为乘势而上开启全面建设社会主义现代化国家新征程指明了前进方向。全国政协各单位和政协委员要认真学习贯彻会议精神，切实把思想和行动统一到以习近平同志为核心的中共中央对形势的科学判断和对工作的部署要求上来，充分发挥专门协商机构作用，围绕把握新发展阶段、贯彻新发展理念、构建新发展格局，结合政协工作实际，组织好协商议政、民主监督和视察考察调研活动，积极建言资政，广泛凝聚共识，为确保“十四五”开好局贡献力量。</p><p>会议审议通过政协全国委员会协商工作规则（草案）。汪洋指出，制定政协协商工作规则是全国政协落实中央政协工作会议精神的实际行动和重要举措。规则对政协协商的主要内容、形式载体、参加范围、讨论原则、基本程序、交流方式等作出规定，是在认真总结人民政协协商工作有益探索和经验做法的基础上，从实践创新到理论创新、制度创新的重要成果，对完善协商于决策之前和决策实施之中的落实机制，更好发挥人民政协专门协商机构作用具有重要意义，按程序通过施行后要在工作中认真落实，在坚持中不断探索完善。</p><p>会议审议通过了全国政协十三届常委会第十五次会议议程（草案）和日程，这次常委会会议为召开全国政协十三届四次会议作准备；审议通过了全国政协十三届四次会议新闻发言人名单，确定全国政协委员、外事委员会委员郭卫民为全国政协十三届四次会议新闻发言人。</p><p>会议听取了全国政协十三届三次会议重点提案督办情况的汇报，各专门委员会工作情况的汇报；审议并原则通过了全国政协2021年协商计划、双周协商座谈会和远程协商会安排等。</p><p>全国政协副主席兼秘书长李斌等就有关议题作了传达、说明和汇报。</p>","logo":"https://p5.img.cctvpic.com/fmspic/2020/12/21/a29f0a0ad92245fd9f56b429ddfe6f70-1.jpg","url":"https://tv.cctv.com/2020/12/21/VIDEM0th5wrG6NHuvBq87cfv201221.shtml","catalog":"","allow_share":"1","allow_praise":"1","allow_comment":"1","channel_id":"CHAL1450952056131267","topic_id":"TOPC1451528971114112","primary_page_id":"PAGE4y8I53JvSWE8DlRSMlbu160121","desc":"汪洋主持召开全国政协主席会议","brief":"汪洋主持召开全国政协主席会议。","tag":"汪洋主持召开全国政协主席会议"}},{"num":8,"video_id":"VIDESvi53IBrhSSMBUNrvEAD201221","video_title":"[视频]《新时代的中国能源发展》白皮书发布","video_image":"https://p1.img.cctvpic.com/fmspic/2020/12/21/a6317b3e297c41f3be72a801919e9cf6-180.jpg","guid":"a6317b3e297c41f3be72a801919e9cf6","video_length":"00:01:20","video_tag":"[视频]《新时代的中国能源发展》白皮书发布","video_url":"https://tv.cctv.com/2020/12/21/VIDESvi53IBrhSSMBUNrvEAD201221.shtml","page_id":"PAGE4y8I53JvSWE8DlRSMlbu160121","edit_mode":"1","brief":"《新时代的中国能源发展》白皮书发布。","pub_date":"2020-12-21 19:23:02","news_hl_tag":"新时代","video_detail":{"id":"VIDESvi53IBrhSSMBUNrvEAD201221","guid":"a6317b3e297c41f3be72a801919e9cf6","title":"[视频]《新时代的中国能源发展》白皮书发布","source":"央视网","pubtime":"2020-12-21 19:23:02","content":"<p>央视网消息（新闻联播）：国务院新闻办公室今天（12月21日）发布《新时代的中国能源发展》白皮书。白皮书指出，党的十八大以来，中国能源生产和利用方式发生重大变革，基本形成了多轮驱动的能源稳定供应体系。能源利用效率显著提高，能源消费结构向清洁低碳加快转变。2012年至2019年，我国以能源消费年均2.8%的增长支撑了国民经济年均7%的增长。清洁能源占能源消费总量比重达到23.4%，比2012年提高8.9个百分点。</p>\r\n<p>能源的绿色发展对碳排放强度下降起到了重要作用，中国2019年碳排放强度比2005年降低48.1%，提前实现了2015年提出的碳排放强度下降40%—45%的目标。</p>","logo":"https://p1.img.cctvpic.com/fmspic/2020/12/21/a6317b3e297c41f3be72a801919e9cf6-180.jpg","url":"https://tv.cctv.com/2020/12/21/VIDESvi53IBrhSSMBUNrvEAD201221.shtml","catalog":"","allow_share":"1","allow_praise":"1","allow_comment":"1","channel_id":"CHAL1450952056131267","topic_id":"TOPC1451528971114112","primary_page_id":"PAGE4y8I53JvSWE8DlRSMlbu160121","desc":"[视频]《新时代的中国能源发展》白皮书发布","brief":"《新时代的中国能源发展》白皮书发布。","tag":"[视频]《新时代的中国能源发展》白皮书发布"}},{"num":9,"video_id":"VIDED3tkGTf3gFMUe8QIDflA201221","video_title":"[视频]防治大气污染 河北唤回蓝天","video_image":"https://p3.img.cctvpic.com/fmspic/2020/12/21/ea83d81ffc4c4b15b8d5db7c6aeab468-180.jpg","guid":"ea83d81ffc4c4b15b8d5db7c6aeab468","video_length":"00:02:56","video_tag":"[视频]防治大气污染,河北唤回蓝天","video_url":"https://tv.cctv.com/2020/12/21/VIDED3tkGTf3gFMUe8QIDflA201221.shtml","page_id":"PAGE4y8I53JvSWE8DlRSMlbu160121","edit_mode":"1","brief":"防治大气污染，河北唤回蓝天。","pub_date":"2020-12-21 19:26:03","news_hl_tag":"","video_detail":{"id":"VIDED3tkGTf3gFMUe8QIDflA201221","guid":"ea83d81ffc4c4b15b8d5db7c6aeab468","title":"[视频]防治大气污染 河北唤回蓝天","source":"央视网","pubtime":"2020-12-21 19:26:03","content":"<p>央视网消息（新闻联播）：河北省一度是京津冀地区污染最严重的省份。近年来，河北省出重拳、下猛药，防治大气污染，让久违的蓝天重回百姓身边。</p>\r\n<p>漫画爱好者师彦文老人用自己的画笔记录着几年来河北大气质量的变化。</p>\r\n<p>2013年全国10个污染最严重城市河北就占了7个，全省重污染天数平均达到73天。</p>\r\n<p>河北省制定了蓝天保卫战三年行动计划，PM2.5浓度下降目标高出全国目标11个百分点；制定了十个行业的地方排放标准，都严于国家标准。</p>\r\n<p>走进这家钢铁厂，很难想象这是一个正在生产的钢铁企业。门前最显眼的是国家4A级旅游景区标志，现代钢铁工艺流程实景展现给游客，这样的底气来源于对环保治理的不断追求。从2017年以来，仅这一家企业就累计减少4000多吨的污染物排放。</p>\r\n<p>秋冬季是北方地区大气污染治理的关键时期。从2019年秋冬季开始，河北省对重点企业进行绩效分级，实行差异化管控。</p>\r\n<p>既保了蓝天，也保了订单，越来越多的企业由“要我改造”变成“我要改造”。治理雾霾不仅要督企，更要督政。2018年以来，河北省有90多个县区市负责人因大气污染治理不力被公开约谈。一子落定，满盘皆活。约谈解决了环保工作当时存在的“上热下冷”、基层落实不力的问题，河北迎来了大气污染治理的新局面。今年1—11月，全省优良天数平均达到234天，比去年同期增加29天，空气质量达到历史同期最好水平，PM2.5平均浓度下降率和优良天数比例提前完成国家下达的“十三五”空气质量改善目标。</p>","logo":"https://p3.img.cctvpic.com/fmspic/2020/12/21/ea83d81ffc4c4b15b8d5db7c6aeab468-180.jpg","url":"https://tv.cctv.com/2020/12/21/VIDED3tkGTf3gFMUe8QIDflA201221.shtml","catalog":"","allow_share":"1","allow_praise":"1","allow_comment":"1","channel_id":"CHAL1450952056131267","topic_id":"TOPC1451528971114112","primary_page_id":"PAGE4y8I53JvSWE8DlRSMlbu160121","desc":"[视频]防治大气污染 河北唤回蓝天","brief":"防治大气污染，河北唤回蓝天。","tag":"[视频]防治大气污染,河北唤回蓝天"}},{"num":10,"video_id":"VIDEPoAIAlmat2r5C6A9VqM4201221","video_title":"[视频]中国记协发布《中国新闻事业发展报告》","video_image":"https://p2.img.cctvpic.com/fmspic/2020/12/21/424cd6f3fe754d2dbca62edb99c610b5-180.jpg","guid":"424cd6f3fe754d2dbca62edb99c610b5","video_length":"00:00:33","video_tag":"[视频]中国记协发布《中国新闻事业发展报告》","video_url":"https://tv.cctv.com/2020/12/21/VIDEPoAIAlmat2r5C6A9VqM4201221.shtml","page_id":"PAGE4y8I53JvSWE8DlRSMlbu160121","edit_mode":"1","brief":"中国记协发布《中国新闻事业发展报告》。","pub_date":"2020-12-21 19:27:02","news_hl_tag":"","video_detail":{"id":"VIDEPoAIAlmat2r5C6A9VqM4201221","guid":"424cd6f3fe754d2dbca62edb99c610b5","title":"[视频]中国记协发布《中国新闻事业发展报告》","source":"央视网","pubtime":"2020-12-21 19:27:02","content":"<p>央视网消息（新闻联播）：中国记协今天（12月21日）发布《中国新闻事业发展报告》，报告显示，面对全媒体时代的机遇和挑战，中国新闻事业加快由传统媒体向全媒体新型平台深度融合转变，各媒体在5G应用、人工智能、4K/8K超高清技术等方面多点布局、推陈出新，融合传播能力迅速提升。此外，2019年全国新闻从业人员数量超过百万，从业人员结构向年轻化、高学历方向发展。</p>","logo":"https://p2.img.cctvpic.com/fmspic/2020/12/21/424cd6f3fe754d2dbca62edb99c610b5-180.jpg","url":"https://tv.cctv.com/2020/12/21/VIDEPoAIAlmat2r5C6A9VqM4201221.shtml","catalog":"","allow_share":"1","allow_praise":"1","allow_comment":"1","channel_id":"CHAL1450952056131267","topic_id":"TOPC1451528971114112","primary_page_id":"PAGE4y8I53JvSWE8DlRSMlbu160121","desc":"[视频]中国记协发布《中国新闻事业发展报告》","brief":"中国记协发布《中国新闻事业发展报告》。","tag":"[视频]中国记协发布《中国新闻事业发展报告》"}},{"num":11,"video_id":"VIDE55sE2hzmdkd5Zks07FSq201221","video_title":"[视频]国务院联防联控机制新闻发布会介绍冬春季疫情防控与重点人群疫苗接种情况","video_image":"https://p3.img.cctvpic.com/fmspic/2020/12/21/78361ba326e143fda46155994a5d4d07-180.jpg","guid":"78361ba326e143fda46155994a5d4d07","video_length":"00:00:57","video_tag":"国务院联防联控机制新闻发布会介绍冬春季疫情防控与重点人群疫苗接种情况","video_url":"https://tv.cctv.com/2020/12/21/VIDE55sE2hzmdkd5Zks07FSq201221.shtml","page_id":"PAGE4y8I53JvSWE8DlRSMlbu160121","edit_mode":"1","brief":"国务院联防联控机制新闻发布会介绍冬春季疫情防控与重点人群疫苗接种情况。","pub_date":"2020-12-21 19:27:03","news_hl_tag":"","video_detail":{"id":"VIDE55sE2hzmdkd5Zks07FSq201221","guid":"78361ba326e143fda46155994a5d4d07","title":"[视频]国务院联防联控机制新闻发布会介绍冬春季疫情防控与重点人群疫苗接种情况","source":"央视网","pubtime":"2020-12-21 19:27:03","content":"<p>央视网消息（新闻联播）：国务院联防联控机制今天（12月21日）举行新闻发布会，介绍冬春季疫情防控与重点人群疫苗接种情况。</p>\r\n<p>国家卫生健康委介绍，“外防输入、内防反弹”仍然是当前疫情防控的重中之重，要继续强化“人物同防”，确保不出现规模性输入和反弹；此外，新冠疫苗存储、运输过程中应当遵守冷链运输储存管理规范，定时监测、记录温度，保证新冠疫苗处于规定的温度环境。</p>","logo":"https://p3.img.cctvpic.com/fmspic/2020/12/21/78361ba326e143fda46155994a5d4d07-180.jpg","url":"https://tv.cctv.com/2020/12/21/VIDE55sE2hzmdkd5Zks07FSq201221.shtml","catalog":"","allow_share":"1","allow_praise":"1","allow_comment":"1","channel_id":"CHAL1450952056131267","topic_id":"TOPC1451528971114112","primary_page_id":"PAGE4y8I53JvSWE8DlRSMlbu160121","desc":"国务院联防联控机制新闻发布会介绍冬春季疫情防控与重点人群疫苗接种情况","brief":"国务院联防联控机制新闻发布会介绍冬春季疫情防控与重点人群疫苗接种情况。","tag":"国务院联防联控机制新闻发布会介绍冬春季疫情防控与重点人群疫苗接种情况"}},{"num":12,"video_id":"VIDESdH6E2SFN0kuRTBEU7hb201221","video_title":"[视频]国家卫生健康委通报最新疫情","video_image":"https://p5.img.cctvpic.com/fmspic/2020/12/21/f507d381ec624816b88316a54890c8be-180.jpg","guid":"f507d381ec624816b88316a54890c8be","video_length":"00:00:32","video_tag":"国家卫生健康委通报最新疫情","video_url":"https://tv.cctv.com/2020/12/21/VIDESdH6E2SFN0kuRTBEU7hb201221.shtml","page_id":"PAGE4y8I53JvSWE8DlRSMlbu160121","edit_mode":"1","brief":"国家卫生健康委通报最新疫情。","pub_date":"2020-12-21 19:27:04","news_hl_tag":"","video_detail":{"id":"VIDESdH6E2SFN0kuRTBEU7hb201221","guid":"f507d381ec624816b88316a54890c8be","title":"[视频]国家卫生健康委通报最新疫情","source":"央视网","pubtime":"2020-12-21 19:27:04","content":"<p>央视网消息（新闻联播）：国家卫生健康委今天（12月21日）通报，12月20日0—24时，31个省（自治区、直辖市）和新疆生产建设兵团报告新增新冠肺炎确诊病例23例，其中境外输入病例21例，本土病例2例；截至12月20日24时，现有确诊病例318例。12月20日0—24时，新增接受医学观察的无症状感染者15例，当日转为确诊病例1例。</p>","logo":"https://p5.img.cctvpic.com/fmspic/2020/12/21/f507d381ec624816b88316a54890c8be-180.jpg","url":"https://tv.cctv.com/2020/12/21/VIDESdH6E2SFN0kuRTBEU7hb201221.shtml","catalog":"","allow_share":"1","allow_praise":"1","allow_comment":"1","channel_id":"CHAL1450952056131267","topic_id":"TOPC1451528971114112","primary_page_id":"PAGE4y8I53JvSWE8DlRSMlbu160121","desc":"国家卫生健康委通报最新疫情","brief":"国家卫生健康委通报最新疫情。","tag":"国家卫生健康委通报最新疫情"}},{"num":13,"video_id":"VIDEKLxh8BMkZAXU56OE6AWQ201221","video_title":"[视频]国内联播快讯","video_image":"https://p2.img.cctvpic.com/fmspic/2020/12/21/02f452de451942de9bb95299930e089b-180.jpg","guid":"02f452de451942de9bb95299930e089b","video_length":"00:02:06","video_tag":"[视频]国内联播快讯","video_url":"https://tv.cctv.com/2020/12/21/VIDEKLxh8BMkZAXU56OE6AWQ201221.shtml","page_id":"PAGE4y8I53JvSWE8DlRSMlbu160121","edit_mode":"1","brief":"国内联播快讯： （1）我国在新办纳税人中实行增值税专票电子化； （2）1—11月我国期货成交量同比增长50.4%； （3）全国铁路明年1月20日实施新的列车运行图； （4）塔里木油田年油气产量突破3000万吨； （5）嫦娥五号搭载的北京冬奥会展示品与公众见面。","pub_date":"2020-12-21 19:30:01","news_hl_tag":"","video_detail":{"id":"VIDEKLxh8BMkZAXU56OE6AWQ201221","guid":"02f452de451942de9bb95299930e089b","title":"[视频]国内联播快讯","source":"央视网","pubtime":"2020-12-21 19:30:01","content":"<p>央视网消息（新闻联播）：</p>\r\n<p>我国在新办纳税人中实行增值税专票电子化</p>\r\n<p>国家税务总局发布公告，从今天（12月21日）起，在天津、河北、上海、江苏、浙江等11个地区的新办纳税人中实行增值税专用发票电子化，这些地区开出的电子专票全国范围内都可以接收使用。从2021年1月21日起，专票电子化将推向全国的新办纳税人。</p>\r\n<p>1—11月我国期货成交量同比增长50.4%</p>\r\n<p>中国期货业协会最新数据显示，1—11月我国期货市场累计成交量、成交额分别为53.8亿手和382.5万亿元，同比分别增长50.4%和45.5%。截止到11月底，我国期货和期权品种共有90个，其中国际化品种6个，为广大实体企业提供了有效的避险工具。</p>\r\n<p>全国铁路明年1月20日实施新的列车运行图</p>\r\n<p>从2021年1月20日零时起，全国铁路将实施新的列车运行图，增开旅客列车325列，主要货运通道增开货物列车114列。调图后，全国铁路客货列车开行总量分别达到10203列、20513列。</p>\r\n<p>塔里木油田年油气产量突破3000万吨</p>\r\n<p>今天（12月21日）零时，位于新疆南部的中国石油塔里木油田年油气产量达到3003.12万吨，全面建成3000万吨大油气田，成为我国油气增产的重要区域。截至目前，塔里木油田探明超深层油气储量超18亿吨，成为我国最大的深层油气田和全球最大超深层凝析油气生产基地。</p>\r\n<p>嫦娥五号搭载的北京冬奥会展示品与公众见面</p>\r\n<p>今天（12月21日），嫦娥五号搭载北京冬奥会展示品交接仪式举行，完成月球之旅的北京2022年冬奥会和冬残奥会会旗、会徽、吉祥物首次与公众见面。下一步，北京冬奥组委将通过举行有关文化活动向公众推广冰雪运动，普及航天知识。</p>","logo":"https://p2.img.cctvpic.com/fmspic/2020/12/21/02f452de451942de9bb95299930e089b-180.jpg","url":"https://tv.cctv.com/2020/12/21/VIDEKLxh8BMkZAXU56OE6AWQ201221.shtml","catalog":"","allow_share":"1","allow_praise":"1","allow_comment":"1","channel_id":"CHAL1450952056131267","topic_id":"TOPC1451528971114112","primary_page_id":"PAGE4y8I53JvSWE8DlRSMlbu160121","desc":"[视频]国内联播快讯","brief":"国内联播快讯： （1）我国在新办纳税人中实行增值税专票电子化； （2）1—11月我国期货成交量同比增长50.4%； （3）全国铁路明年1月20日实施新的列车运行图； （4）塔里木油田年油气产量突破3000万吨； （5）嫦娥五号搭载的北京冬奥会展示品与公众见面。","tag":"[视频]国内联播快讯"}},{"num":14,"video_id":"VIDEptUlWtqoaUb1x1mh5ElT201221","video_title":"[视频]全球累计新冠肺炎确诊病例超7510万","video_image":"https://p5.img.cctvpic.com/fmspic/2020/12/21/8f1a5fbebd2a4181914e0f491b8c8ed2-180.jpg","guid":"8f1a5fbebd2a4181914e0f491b8c8ed2","video_length":"00:01:29","video_tag":"[视频]全球累计新冠肺炎确诊病例超7510万","video_url":"https://tv.cctv.com/2020/12/21/VIDEptUlWtqoaUb1x1mh5ElT201221.shtml","page_id":"PAGE4y8I53JvSWE8DlRSMlbu160121","edit_mode":"1","brief":"全球累计新冠肺炎确诊病例超7510万；美确诊病例超1784万，病床紧缺；美疫情严重冲击经济，部分民众苦不堪言。","pub_date":"2020-12-21 19:31:02","news_hl_tag":"","video_detail":{"id":"VIDEptUlWtqoaUb1x1mh5ElT201221","guid":"8f1a5fbebd2a4181914e0f491b8c8ed2","title":"[视频]全球累计新冠肺炎确诊病例超7510万","source":"央视网","pubtime":"2020-12-21 19:31:02","content":"<p>央视网消息（新闻联播）：根据世界卫生组织的统计数据，全球累计新冠肺炎确诊病例达到75110651例，累计死亡病例为1680395例。20日全球新冠肺炎确诊病例比前一天新增808224例，为新高。</p>\r\n<p>美确诊病例超1748万 病床紧缺</p>\r\n<p>截至北京时间今天（12月21日）16时，美国累计确诊病例数为17844839例，死亡病例为317670例。20日，美国报告单日新增确诊病例为189099例。</p>\r\n<p>在美国人口最多的州，也是疫情最重的加州，可用的重症监护床位只有大约2.1%，救护车要等待7个小时才能把病人送进急诊室。</p>\r\n<p>美疫情严重冲击经济 部分民众苦不堪言</p>\r\n<p>严重疫情还对不少美国民众的生活持续造成冲击，他们不得不在“吃饱肚子和付房租”之间作出选择。</p>","logo":"https://p5.img.cctvpic.com/fmspic/2020/12/21/8f1a5fbebd2a4181914e0f491b8c8ed2-180.jpg","url":"https://tv.cctv.com/2020/12/21/VIDEptUlWtqoaUb1x1mh5ElT201221.shtml","catalog":"","allow_share":"1","allow_praise":"1","allow_comment":"1","channel_id":"CHAL1450952056131267","topic_id":"TOPC1451528971114112","primary_page_id":"PAGE4y8I53JvSWE8DlRSMlbu160121","desc":"[视频]全球累计新冠肺炎确诊病例超7510万","brief":"全球累计新冠肺炎确诊病例超7510万；美确诊病例超1784万，病床紧缺；美疫情严重冲击经济，部分民众苦不堪言。","tag":"[视频]全球累计新冠肺炎确诊病例超7510万"}},{"num":15,"video_id":"VIDE3L7eKnGBWfKOui4kol4r201221","video_title":"[视频]英政府承认变异病毒在英传播失控","video_image":"https://p4.img.cctvpic.com/fmspic/2020/12/21/ba19bde020784936aea5d0aaf8e77017-180.jpg","guid":"ba19bde020784936aea5d0aaf8e77017","video_length":"00:01:41","video_tag":"[视频]英政府承认变异病毒在英传播失控","video_url":"https://tv.cctv.com/2020/12/21/VIDE3L7eKnGBWfKOui4kol4r201221.shtml","page_id":"PAGE4y8I53JvSWE8DlRSMlbu160121","edit_mode":"1","brief":"英政府承认变异病毒在英传播失控；多国对英国关闭边境、限制人员。","pub_date":"2020-12-21 19:34:03","news_hl_tag":"国际资讯","video_detail":{"id":"VIDE3L7eKnGBWfKOui4kol4r201221","guid":"ba19bde020784936aea5d0aaf8e77017","title":"[视频]英政府承认变异病毒在英传播失控","source":"央视网","pubtime":"2020-12-21 19:34:03","content":"<p>央视网消息（新闻联播）：英国政府20日公布的数据显示，英国单日新增确诊病例达到35928例，累计病例超过204万。英国政府方面20日承认，一种变异新冠病毒在英国的传播已经失控。</p>\r\n<p>英国医学专家表示，这种变异病毒的传播速度比之前要快大约70%。不过，目前研究显示，变异病毒可能不会引发更严重的病症，也不会影响疫苗的效用。</p>\r\n<p>英国科研人员9月在一名患者身上发现这种变异病毒。英国政府本月14日公布了出现变异病毒的情况。世界卫生组织紧急项目技术负责人玛丽亚·范·科霍夫20日证实，变异病毒发现自英格兰东南部。目前，丹麦、荷兰、意大利以及澳大利亚也发现了相关确诊病例。</p>\r\n<p>英国从20日起，将首都伦敦、英格兰东南部和东部部分地区的新冠疫情防控级别从第三级提升至新增加的第四级，为期两周。当地时间19日晚，伦敦等地的不少居民赶在新措施生效前进行新年前的采购，还有大约二三十万人通过铁路、公路等方式离开伦敦，均出现严重聚集。</p>\r\n<p>多国对英国关闭边境 限制人员</p>\r\n<p>20日，包括法国、德国、意大利、爱尔兰等欧洲国家在内的世界多个国家都采取措施暂停英国航班、轮船等入境。</p>","logo":"https://p4.img.cctvpic.com/fmspic/2020/12/21/ba19bde020784936aea5d0aaf8e77017-180.jpg","url":"https://tv.cctv.com/2020/12/21/VIDE3L7eKnGBWfKOui4kol4r201221.shtml","catalog":"","allow_share":"1","allow_praise":"1","allow_comment":"1","channel_id":"CHAL1450952056131267","topic_id":"TOPC1451528971114112","primary_page_id":"PAGE4y8I53JvSWE8DlRSMlbu160121","desc":"[视频]英政府承认变异病毒在英传播失控","brief":"英政府承认变异病毒在英传播失控；多国对英国关闭边境、限制人员。","tag":"[视频]英政府承认变异病毒在英传播失控"}},{"num":16,"video_id":"VIDElBlMEcqGuY3R90x9QtUb201221","video_title":"[视频]国际联播快讯","video_image":"https://p1.img.cctvpic.com/fmspic/2020/12/21/5d274b1736ea47109fbaac7e3018533e-180.jpg","guid":"5d274b1736ea47109fbaac7e3018533e","video_length":"00:00:56","video_tag":"[视频]国际联播快讯","video_url":"https://tv.cctv.com/2020/12/21/VIDElBlMEcqGuY3R90x9QtUb201221.shtml","page_id":"PAGE4y8I53JvSWE8DlRSMlbu160121","edit_mode":"1","brief":"国际联播快讯： （1）普京敦促俄安全机构灵活应对国际局势； （2）巴格达“绿区”遭袭，美使馆受损。","pub_date":"2020-12-21 19:35:02","news_hl_tag":"国际资讯","video_detail":{"id":"VIDElBlMEcqGuY3R90x9QtUb201221","guid":"5d274b1736ea47109fbaac7e3018533e","title":"[视频]国际联播快讯","source":"央视网","pubtime":"2020-12-21 19:35:02","content":"<p>央视网消息（新闻联播）：</p>\r\n<p>普京敦促俄安全机构灵活应对国际局势</p>\r\n<p>20日，俄罗斯总统普京在视察俄罗斯对外情报局总部时发表讲话，要求情报机构灵活应对，识别复杂变化的国际局势，化解针对俄罗斯的潜在威胁，继续坚决打击恐怖主义和极端主义。普京还说，俄罗斯边境存在突发冲突的风险，情报机构应该有效确保俄罗斯边境安全。</p>\r\n<p>巴格达“绿区”遭袭 美使馆受损</p>\r\n<p>当地时间20日晚间，伊拉克首都巴格达市中心“绿区”遭数枚火箭弹袭击，部分建筑和车辆受损。伊拉克军方称，袭击没有造成人员伤亡。美国使馆证实，袭击造成使馆部分设施轻微受损。还没有任何组织或个人宣称制造了这起袭击事件。</p>\r\n<p>“绿区”是伊拉克政府机构以及美英等国驻伊大使馆所在地，针对“绿区”的袭击事件时有发生。</p>","logo":"https://p1.img.cctvpic.com/fmspic/2020/12/21/5d274b1736ea47109fbaac7e3018533e-180.jpg","url":"https://tv.cctv.com/2020/12/21/VIDElBlMEcqGuY3R90x9QtUb201221.shtml","catalog":"","allow_share":"1","allow_praise":"1","allow_comment":"1","channel_id":"CHAL1450952056131267","topic_id":"TOPC1451528971114112","primary_page_id":"PAGE4y8I53JvSWE8DlRSMlbu160121","desc":"[视频]国际联播快讯","brief":"国际联播快讯： （1）普京敦促俄安全机构灵活应对国际局势； （2）巴格达“绿区”遭袭，美使馆受损。","tag":"[视频]国际联播快讯"}}]}
